damv1kubectl/__init__.py
damv1kubectl/production_mykubectl_series_1.py
damv1kubectl/production_mykubectl_series_2.py
damv1kubectl/sandbox_mykubectl_series_1.py
damv1kubectl/sandbox_mykubectl_series_2.py
damv1kubectl-0.8.22.dist-info/METADATA
damv1kubectl-0.8.22.dist-info/WHEEL
damv1kubectl-0.8.22.dist-info/top_level.txt
damv1kubectl-0.8.22.dist-info/RECORD
